<?xml version="1.0"?>
<!DOCTYPE hibernate-mapping PUBLIC "-//Hibernate/Hibernate Mapping DTD 3.0//EN"
		"http://hibernate.org/dtd/hibernate-mapping-3.0.dtd">

<hibernate-mapping>
	<class name="fr.test.hibernate.entities.Personne" table="table1">
		<id name="nom" >
			<column name="nom" />
		</id>
		<property name="nom" type="java.lang.String">
			<column name="nom" />
		</property>
		<property name="prenom" type="java.lang.String">
			<column name="prenom" />
		</property>
		<property name="age" type="int">
			<column name="age" />
		</property>
	</class>
</hibernate-mapping>